corpus_unpdf/__init__.py
corpus_unpdf/_markers.py
corpus_unpdf/_positions.py
corpus_unpdf/main.py
corpus_unpdf-0.1.0.dist-info/METADATA
corpus_unpdf-0.1.0.dist-info/WHEEL
corpus_unpdf-0.1.0.dist-info/RECORD
