Metadata-Version: 2.1
Name: corpus-unpdf
Version: 0.1.0
Summary: Parse Philippine Supreme Court decisions issued in PDF format as text.
Home-page: https://lawsql.com
License: MIT
Author: Marcelino G. Veloso III
Author-email: mars@veloso.one
Requires-Python: >=3.11,<4.0
Classifier: Development Status :: 4 - Beta
Classifier: Framework :: Pytest
Classifier: Intended Audience :: Legal Industry
Classifier: License :: OSI Approved :: MIT License
Classifier: Programming Language :: Python :: 3
Classifier: Programming Language :: Python :: 3.11
Classifier: Topic :: Scientific/Engineering :: Image Processing
Classifier: Topic :: Scientific/Engineering :: Information Analysis
Classifier: Typing :: Typed
Requires-Dist: start-ocr (>=0.0.3,<0.0.4)
Project-URL: Documentation, https://justmars.github.io/corpus-unpdf
Project-URL: Repository, https://github.com/justmars/corpus-unpdf
